theabbie/__init__.py
theabbie/__main__.py
theabbie-1.1.0.dist-info/METADATA
theabbie-1.1.0.dist-info/WHEEL
theabbie-1.1.0.dist-info/entry_points.txt
theabbie-1.1.0.dist-info/top_level.txt
theabbie-1.1.0.dist-info/RECORD
