Metadata-Version: 2.1
Name: theabbie
Version: 1.1.0
Summary: a pseudo-introvert, a web developer, and a maker
Home-page: https://theabbie.github.io
Author: TheAbbie
Author-email: abhishek7gg7@gmail.com
License: MIT
Platform: UNKNOWN
Classifier: License :: OSI Approved :: MIT License
Classifier: Programming Language :: Python
Classifier: Programming Language :: Python :: 2
Classifier: Programming Language :: Python :: 3
Requires-Dist: importlib-resources
